xxtea/__init__.py
xxtea/xxtea.c
xxtea/xxtea.h
xxtea_py-1.0.3.dist-info/DESCRIPTION.rst
xxtea_py-1.0.3.dist-info/METADATA
xxtea_py-1.0.3.dist-info/RECORD
xxtea_py-1.0.3.dist-info/WHEEL
xxtea_py-1.0.3.dist-info/metadata.json
xxtea_py-1.0.3.dist-info/top_level.txt
