Metadata-Version: 2.0
Name: xxtea-py
Version: 1.0.3
Summary: XXTEA is a fast and secure encryption algorithm. This is a XXTEA library for Python. It is based on CFFI, so it is fast and support both cpython and pypy.
Home-page: https://github.com/xxtea/xxtea-python
Author: Ma Bingyao
Author-email: mabingyao@gmail.com
License: MIT
Keywords: xxtea crypt encrypt decrypt xtea tea
Platform: any
Classifier: Development Status :: 5 - Production/Stable
Classifier: Intended Audience :: Developers
Classifier: Programming Language :: Python :: 2.6
Classifier: Programming Language :: Python :: 2.7
Classifier: Programming Language :: Python :: 3
Classifier: Programming Language :: Python :: 3.2
Classifier: Programming Language :: Python :: 3.3
Classifier: Programming Language :: Python :: 3.4
Classifier: Programming Language :: Python :: 3.5
Classifier: Programming Language :: Python :: 3.6
Classifier: Programming Language :: Python :: 3.7
Classifier: License :: OSI Approved :: MIT License
Classifier: Programming Language :: Python :: Implementation :: CPython
Classifier: Programming Language :: Python :: Implementation :: PyPy
Classifier: Operating System :: OS Independent
